{
  "population": "AFR",
  "emission_params": {
    "n_observations": 18963538,
    "full_distribution": {
      "mean": 0.9946297294652349,
      "std": 0.04405568710564748,
      "median": 0.9986002,
      "min": 0.000272,
      "max": 1.0
    },
    "non_ibd": {
      "mean": 0.9984448589360427,
      "std": 0.001024951680023231,
      "robust_std": 0.0013350813000001212
    },
    "ibd": {
      "mean": 0.9998127581123332,
      "std": 0.000171086223964926,
      "n_samples": 4423789
    },
    "d_prime": 1.8616504503302391,
    "fraction_above_thresholds": {
      "0.999": 0.3967210654467537,
      "0.9995": 0.2332786740533333,
      "0.9999": 0.09605259313952913
    }
  },
  "n_pairs": 50,
  "results": [
    {
      "sample_a": "NA18522",
      "hap_a": 2,
      "sample_b": "NA19700",
      "hap_b": 2,
      "chrom": "CHM13#0#chr2",
      "n_windows": 10000,
      "log_likelihood": -7324600.075560538,
      "n_segments": 0,
      "total_ibd_bp": 0,
      "fraction_ibd": 0.0,
      "mean_segment_length": 0.0,
      "segments": []
    },
    {
      "sample_a": "NA19043",
      "hap_a": 2,
      "sample_b": "NA19700",
      "hap_b": 2,
      "chrom": "CHM13#0#chr2",
      "n_windows": 10000,
      "log_likelihood": -7307391.907456889,
      "n_segments": 0,
      "total_ibd_bp": 0,
      "fraction_ibd": 0.0,
      "mean_segment_length": 0.0,
      "segments": []
    },
    {
      "sample_a": "HG02583",
      "hap_a": 1,
      "sample_b": "NA19700",
      "hap_b": 2,
      "chrom": "CHM13#0#chr2",
      "n_windows": 10000,
      "log_likelihood": -6838148.579960499,
      "n_segments": 0,
      "total_ibd_bp": 0,
      "fraction_ibd": 0.0,
      "mean_segment_length": 0.0,
      "segments": []
    },
    {
      "sample_a": "NA19043",
      "hap_a": 2,
      "sample_b": "NA19338",
      "hap_b": 2,
      "chrom": "CHM13#0#chr2",
      "n_windows": 10000,
      "log_likelihood": -6589982.848851855,
      "n_segments": 0,
      "total_ibd_bp": 0,
      "fraction_ibd": 0.0,
      "mean_segment_length": 0.0,
      "segments": []
    },
    {
      "sample_a": "HG02583",
      "hap_a": 1,
      "sample_b": "NA19043",
      "hap_b": 2,
      "chrom": "CHM13#0#chr2",
      "n_windows": 10000,
      "log_likelihood": -6506468.466959319,
      "n_segments": 0,
      "total_ibd_bp": 0,
      "fraction_ibd": 0.0,
      "mean_segment_length": 0.0,
      "segments": []
    },
    {
      "sample_a": "NA19700",
      "hap_a": 1,
      "sample_b": "NA19700",
      "hap_b": 2,
      "chrom": "CHM13#0#chr2",
      "n_windows": 10000,
      "log_likelihood": -6498827.924994948,
      "n_segments": 0,
      "total_ibd_bp": 0,
      "fraction_ibd": 0.0,
      "mean_segment_length": 0.0,
      "segments": []
    },
    {
      "sample_a": "NA19700",
      "hap_a": 2,
      "sample_b": "NA20282",
      "hap_b": 2,
      "chrom": "CHM13#0#chr2",
      "n_windows": 10000,
      "log_likelihood": -6498879.868260865,
      "n_segments": 0,
      "total_ibd_bp": 0,
      "fraction_ibd": 0.0,
      "mean_segment_length": 0.0,
      "segments": []
    },
    {
      "sample_a": "HG02583",
      "hap_a": 1,
      "sample_b": "NA19338",
      "hap_b": 2,
      "chrom": "CHM13#0#chr2",
      "n_windows": 10000,
      "log_likelihood": -6409348.479337331,
      "n_segments": 0,
      "total_ibd_bp": 0,
      "fraction_ibd": 0.0,
      "mean_segment_length": 0.0,
      "segments": []
    },
    {
      "sample_a": "HG03521",
      "hap_a": 1,
      "sample_b": "NA19700",
      "hap_b": 2,
      "chrom": "CHM13#0#chr2",
      "n_windows": 10000,
      "log_likelihood": -6390962.871206935,
      "n_segments": 0,
      "total_ibd_bp": 0,
      "fraction_ibd": 0.0,
      "mean_segment_length": 0.0,
      "segments": []
    },
    {
      "sample_a": "HG03470",
      "hap_a": 1,
      "sample_b": "NA19700",
      "hap_b": 2,
      "chrom": "CHM13#0#chr2",
      "n_windows": 10000,
      "log_likelihood": -6317895.068280428,
      "n_segments": 0,
      "total_ibd_bp": 0,
      "fraction_ibd": 0.0,
      "mean_segment_length": 0.0,
      "segments": []
    },
    {
      "sample_a": "HG03583",
      "hap_a": 1,
      "sample_b": "NA19700",
      "hap_b": 2,
      "chrom": "CHM13#0#chr2",
      "n_windows": 10000,
      "log_likelihood": -6305595.9689087905,
      "n_segments": 0,
      "total_ibd_bp": 0,
      "fraction_ibd": 0.0,
      "mean_segment_length": 0.0,
      "segments": []
    },
    {
      "sample_a": "NA18522",
      "hap_a": 2,
      "sample_b": "NA19043",
      "hap_b": 2,
      "chrom": "CHM13#0#chr2",
      "n_windows": 10000,
      "log_likelihood": -6239420.0114217475,
      "n_segments": 0,
      "total_ibd_bp": 0,
      "fraction_ibd": 0.0,
      "mean_segment_length": 0.0,
      "segments": []
    },
    {
      "sample_a": "NA19700",
      "hap_a": 1,
      "sample_b": "NA19835",
      "hap_b": 1,
      "chrom": "CHM13#0#chr2",
      "n_windows": 10000,
      "log_likelihood": -6228393.173984552,
      "n_segments": 0,
      "total_ibd_bp": 0,
      "fraction_ibd": 0.0,
      "mean_segment_length": 0.0,
      "segments": []
    },
    {
      "sample_a": "HG02583",
      "hap_a": 1,
      "sample_b": "NA19700",
      "hap_b": 1,
      "chrom": "CHM13#0#chr2",
      "n_windows": 10000,
      "log_likelihood": -6222162.55781797,
      "n_segments": 0,
      "total_ibd_bp": 0,
      "fraction_ibd": 0.0,
      "mean_segment_length": 0.0,
      "segments": []
    },
    {
      "sample_a": "HG03521",
      "hap_a": 1,
      "sample_b": "NA19338",
      "hap_b": 2,
      "chrom": "CHM13#0#chr2",
      "n_windows": 10000,
      "log_likelihood": -6129867.344962357,
      "n_segments": 0,
      "total_ibd_bp": 0,
      "fraction_ibd": 0.0,
      "mean_segment_length": 0.0,
      "segments": []
    },
    {
      "sample_a": "HG03139",
      "hap_a": 2,
      "sample_b": "NA19700",
      "hap_b": 2,
      "chrom": "CHM13#0#chr2",
      "n_windows": 10000,
      "log_likelihood": -6141117.253041428,
      "n_segments": 0,
      "total_ibd_bp": 0,
      "fraction_ibd": 0.0,
      "mean_segment_length": 0.0,
      "segments": []
    },
    {
      "sample_a": "NA19043",
      "hap_a": 2,
      "sample_b": "NA20282",
      "hap_b": 2,
      "chrom": "CHM13#0#chr2",
      "n_windows": 10000,
      "log_likelihood": -6128185.028807788,
      "n_segments": 0,
      "total_ibd_bp": 0,
      "fraction_ibd": 0.0,
      "mean_segment_length": 0.0,
      "segments": []
    },
    {
      "sample_a": "NA19443",
      "hap_a": 2,
      "sample_b": "NA19700",
      "hap_b": 2,
      "chrom": "CHM13#0#chr2",
      "n_windows": 10000,
      "log_likelihood": -6089871.516818653,
      "n_segments": 0,
      "total_ibd_bp": 0,
      "fraction_ibd": 0.0,
      "mean_segment_length": 0.0,
      "segments": []
    },
    {
      "sample_a": "NA19338",
      "hap_a": 2,
      "sample_b": "NA19835",
      "hap_b": 1,
      "chrom": "CHM13#0#chr2",
      "n_windows": 10000,
      "log_likelihood": -6000539.545099688,
      "n_segments": 0,
      "total_ibd_bp": 0,
      "fraction_ibd": 0.0,
      "mean_segment_length": 0.0,
      "segments": []
    },
    {
      "sample_a": "HG02922",
      "hap_a": 2,
      "sample_b": "NA19700",
      "hap_b": 2,
      "chrom": "CHM13#0#chr2",
      "n_windows": 10000,
      "log_likelihood": -6008494.381658801,
      "n_segments": 0,
      "total_ibd_bp": 0,
      "fraction_ibd": 0.0,
      "mean_segment_length": 0.0,
      "segments": []
    },
    {
      "sample_a": "NA18522",
      "hap_a": 2,
      "sample_b": "NA19835",
      "hap_b": 1,
      "chrom": "CHM13#0#chr2",
      "n_windows": 10000,
      "log_likelihood": -5999746.529143572,
      "n_segments": 0,
      "total_ibd_bp": 0,
      "fraction_ibd": 0.0,
      "mean_segment_length": 0.0,
      "segments": []
    },
    {
      "sample_a": "HG03139",
      "hap_a": 2,
      "sample_b": "NA19043",
      "hap_b": 2,
      "chrom": "CHM13#0#chr2",
      "n_windows": 10000,
      "log_likelihood": -5942408.070902799,
      "n_segments": 0,
      "total_ibd_bp": 0,
      "fraction_ibd": 0.0,
      "mean_segment_length": 0.0,
      "segments": []
    },
    {
      "sample_a": "HG02583",
      "hap_a": 1,
      "sample_b": "NA19036",
      "hap_b": 1,
      "chrom": "CHM13#0#chr2",
      "n_windows": 10000,
      "log_likelihood": -5933379.692152191,
      "n_segments": 0,
      "total_ibd_bp": 0,
      "fraction_ibd": 0.0,
      "mean_segment_length": 0.0,
      "segments": []
    },
    {
      "sample_a": "HG02583",
      "hap_a": 1,
      "sample_b": "HG03369",
      "hap_b": 2,
      "chrom": "CHM13#0#chr2",
      "n_windows": 10000,
      "log_likelihood": -5929314.680808823,
      "n_segments": 0,
      "total_ibd_bp": 0,
      "fraction_ibd": 0.0,
      "mean_segment_length": 0.0,
      "segments": []
    },
    {
      "sample_a": "NA19338",
      "hap_a": 2,
      "sample_b": "NA19700",
      "hap_b": 1,
      "chrom": "CHM13#0#chr2",
      "n_windows": 10000,
      "log_likelihood": -5893755.290602631,
      "n_segments": 0,
      "total_ibd_bp": 0,
      "fraction_ibd": 0.0,
      "mean_segment_length": 0.0,
      "segments": []
    },
    {
      "sample_a": "HG02583",
      "hap_a": 1,
      "sample_b": "NA18522",
      "hap_b": 2,
      "chrom": "CHM13#0#chr2",
      "n_windows": 10000,
      "log_likelihood": -5903236.921332886,
      "n_segments": 0,
      "total_ibd_bp": 0,
      "fraction_ibd": 0.0,
      "mean_segment_length": 0.0,
      "segments": []
    },
    {
      "sample_a": "HG02583",
      "hap_a": 1,
      "sample_b": "HG02976",
      "hap_b": 1,
      "chrom": "CHM13#0#chr2",
      "n_windows": 10000,
      "log_likelihood": -5880427.4386434,
      "n_segments": 0,
      "total_ibd_bp": 0,
      "fraction_ibd": 0.0,
      "mean_segment_length": 0.0,
      "segments": []
    },
    {
      "sample_a": "HG03130",
      "hap_a": 2,
      "sample_b": "NA19700",
      "hap_b": 2,
      "chrom": "CHM13#0#chr2",
      "n_windows": 10000,
      "log_likelihood": -5871732.911290696,
      "n_segments": 0,
      "total_ibd_bp": 0,
      "fraction_ibd": 0.0,
      "mean_segment_length": 0.0,
      "segments": []
    },
    {
      "sample_a": "NA19185",
      "hap_a": 2,
      "sample_b": "NA19338",
      "hap_b": 2,
      "chrom": "CHM13#0#chr2",
      "n_windows": 10000,
      "log_likelihood": -5822642.103978995,
      "n_segments": 0,
      "total_ibd_bp": 0,
      "fraction_ibd": 0.0,
      "mean_segment_length": 0.0,
      "segments": []
    },
    {
      "sample_a": "HG03195",
      "hap_a": 1,
      "sample_b": "NA19700",
      "hap_b": 2,
      "chrom": "CHM13#0#chr2",
      "n_windows": 10000,
      "log_likelihood": -5807654.848030974,
      "n_segments": 0,
      "total_ibd_bp": 0,
      "fraction_ibd": 0.0,
      "mean_segment_length": 0.0,
      "segments": []
    },
    {
      "sample_a": "NA18522",
      "hap_a": 2,
      "sample_b": "NA19338",
      "hap_b": 2,
      "chrom": "CHM13#0#chr2",
      "n_windows": 10000,
      "log_likelihood": -5768639.23644757,
      "n_segments": 0,
      "total_ibd_bp": 0,
      "fraction_ibd": 0.0,
      "mean_segment_length": 0.0,
      "segments": []
    },
    {
      "sample_a": "HG02583",
      "hap_a": 1,
      "sample_b": "NA19338",
      "hap_b": 1,
      "chrom": "CHM13#0#chr2",
      "n_windows": 10000,
      "log_likelihood": -5771898.341830838,
      "n_segments": 0,
      "total_ibd_bp": 0,
      "fraction_ibd": 0.0,
      "mean_segment_length": 0.0,
      "segments": []
    },
    {
      "sample_a": "NA18508",
      "hap_a": 1,
      "sample_b": "NA19700",
      "hap_b": 2,
      "chrom": "CHM13#0#chr2",
      "n_windows": 10000,
      "log_likelihood": -5757015.912898167,
      "n_segments": 0,
      "total_ibd_bp": 0,
      "fraction_ibd": 0.0,
      "mean_segment_length": 0.0,
      "segments": []
    },
    {
      "sample_a": "NA19338",
      "hap_a": 2,
      "sample_b": "NA19700",
      "hap_b": 2,
      "chrom": "CHM13#0#chr2",
      "n_windows": 10000,
      "log_likelihood": -5723327.824472473,
      "n_segments": 0,
      "total_ibd_bp": 0,
      "fraction_ibd": 0.0,
      "mean_segment_length": 0.0,
      "segments": []
    },
    {
      "sample_a": "HG03195",
      "hap_a": 1,
      "sample_b": "NA19043",
      "hap_b": 2,
      "chrom": "CHM13#0#chr2",
      "n_windows": 10000,
      "log_likelihood": -5710338.993952442,
      "n_segments": 0,
      "total_ibd_bp": 0,
      "fraction_ibd": 0.0,
      "mean_segment_length": 0.0,
      "segments": []
    },
    {
      "sample_a": "NA18522",
      "hap_a": 2,
      "sample_b": "NA19700",
      "hap_b": 1,
      "chrom": "CHM13#0#chr2",
      "n_windows": 10000,
      "log_likelihood": -5708417.024617889,
      "n_segments": 0,
      "total_ibd_bp": 0,
      "fraction_ibd": 0.0,
      "mean_segment_length": 0.0,
      "segments": []
    },
    {
      "sample_a": "HG02965",
      "hap_a": 1,
      "sample_b": "NA19700",
      "hap_b": 2,
      "chrom": "CHM13#0#chr2",
      "n_windows": 10000,
      "log_likelihood": -5697311.377738679,
      "n_segments": 0,
      "total_ibd_bp": 0,
      "fraction_ibd": 0.0,
      "mean_segment_length": 0.0,
      "segments": []
    },
    {
      "sample_a": "NA19391",
      "hap_a": 2,
      "sample_b": "NA19700",
      "hap_b": 2,
      "chrom": "CHM13#0#chr2",
      "n_windows": 10000,
      "log_likelihood": -5699176.858967672,
      "n_segments": 0,
      "total_ibd_bp": 0,
      "fraction_ibd": 0.0,
      "mean_segment_length": 0.0,
      "segments": []
    },
    {
      "sample_a": "NA19043",
      "hap_a": 2,
      "sample_b": "NA19909",
      "hap_b": 2,
      "chrom": "CHM13#0#chr2",
      "n_windows": 10000,
      "log_likelihood": -5701429.369941333,
      "n_segments": 0,
      "total_ibd_bp": 0,
      "fraction_ibd": 0.0,
      "mean_segment_length": 0.0,
      "segments": []
    },
    {
      "sample_a": "NA19700",
      "hap_a": 2,
      "sample_b": "NA19909",
      "hap_b": 1,
      "chrom": "CHM13#0#chr2",
      "n_windows": 10000,
      "log_likelihood": -5680997.506453465,
      "n_segments": 0,
      "total_ibd_bp": 0,
      "fraction_ibd": 0.0,
      "mean_segment_length": 0.0,
      "segments": []
    },
    {
      "sample_a": "NA19338",
      "hap_a": 2,
      "sample_b": "NA19391",
      "hap_b": 2,
      "chrom": "CHM13#0#chr2",
      "n_windows": 10000,
      "log_likelihood": -5663248.385545111,
      "n_segments": 0,
      "total_ibd_bp": 0,
      "fraction_ibd": 0.0,
      "mean_segment_length": 0.0,
      "segments": []
    },
    {
      "sample_a": "HG02583",
      "hap_a": 1,
      "sample_b": "NA19159",
      "hap_b": 2,
      "chrom": "CHM13#0#chr2",
      "n_windows": 10000,
      "log_likelihood": -5666142.616548787,
      "n_segments": 0,
      "total_ibd_bp": 0,
      "fraction_ibd": 0.0,
      "mean_segment_length": 0.0,
      "segments": []
    },
    {
      "sample_a": "HG03195",
      "hap_a": 1,
      "sample_b": "NA19700",
      "hap_b": 1,
      "chrom": "CHM13#0#chr2",
      "n_windows": 10000,
      "log_likelihood": -5657580.186059298,
      "n_segments": 0,
      "total_ibd_bp": 0,
      "fraction_ibd": 0.0,
      "mean_segment_length": 0.0,
      "segments": []
    },
    {
      "sample_a": "HG02583",
      "hap_a": 1,
      "sample_b": "HG03130",
      "hap_b": 2,
      "chrom": "CHM13#0#chr2",
      "n_windows": 10000,
      "log_likelihood": -5616200.885483913,
      "n_segments": 0,
      "total_ibd_bp": 0,
      "fraction_ibd": 0.0,
      "mean_segment_length": 0.0,
      "segments": []
    },
    {
      "sample_a": "HG03139",
      "hap_a": 2,
      "sample_b": "NA19338",
      "hap_b": 2,
      "chrom": "CHM13#0#chr2",
      "n_windows": 10000,
      "log_likelihood": -5588574.113079588,
      "n_segments": 0,
      "total_ibd_bp": 0,
      "fraction_ibd": 0.0,
      "mean_segment_length": 0.0,
      "segments": []
    },
    {
      "sample_a": "NA19391",
      "hap_a": 1,
      "sample_b": "NA19700",
      "hap_b": 2,
      "chrom": "CHM13#0#chr2",
      "n_windows": 10000,
      "log_likelihood": -5599300.925728012,
      "n_segments": 0,
      "total_ibd_bp": 0,
      "fraction_ibd": 0.0,
      "mean_segment_length": 0.0,
      "segments": []
    },
    {
      "sample_a": "NA18879",
      "hap_a": 2,
      "sample_b": "NA19700",
      "hap_b": 2,
      "chrom": "CHM13#0#chr2",
      "n_windows": 10000,
      "log_likelihood": -5591157.471689232,
      "n_segments": 0,
      "total_ibd_bp": 0,
      "fraction_ibd": 0.0,
      "mean_segment_length": 0.0,
      "segments": []
    },
    {
      "sample_a": "NA19700",
      "hap_a": 1,
      "sample_b": "NA20282",
      "hap_b": 2,
      "chrom": "CHM13#0#chr2",
      "n_windows": 10000,
      "log_likelihood": -5554425.154470452,
      "n_segments": 0,
      "total_ibd_bp": 0,
      "fraction_ibd": 0.0,
      "mean_segment_length": 0.0,
      "segments": []
    },
    {
      "sample_a": "HG02583",
      "hap_a": 1,
      "sample_b": "HG03583",
      "hap_b": 1,
      "chrom": "CHM13#0#chr2",
      "n_windows": 10000,
      "log_likelihood": -5550426.61604262,
      "n_segments": 0,
      "total_ibd_bp": 0,
      "fraction_ibd": 0.0,
      "mean_segment_length": 0.0,
      "segments": []
    },
    {
      "sample_a": "NA18522",
      "hap_a": 2,
      "sample_b": "NA20346",
      "hap_b": 2,
      "chrom": "CHM13#0#chr2",
      "n_windows": 10000,
      "log_likelihood": -5530489.027165725,
      "n_segments": 0,
      "total_ibd_bp": 0,
      "fraction_ibd": 0.0,
      "mean_segment_length": 0.0,
      "segments": []
    }
  ]
}